django_phaxio/__init__.py
django_phaxio/conf.py
django_phaxio/signals.py
django_phaxio/urls.py
django_phaxio/views.py
django_phaxio-4.0.0.dist-info/AUTHORS
django_phaxio-4.0.0.dist-info/LICENSE
django_phaxio-4.0.0.dist-info/METADATA
django_phaxio-4.0.0.dist-info/WHEEL
django_phaxio-4.0.0.dist-info/pbr.json
django_phaxio-4.0.0.dist-info/top_level.txt
django_phaxio-4.0.0.dist-info/RECORD
