Metadata-Version: 2.1
Name: django-phaxio
Version: 4.0.0
Summary: A Django WebHook handler for Phaxio.
Home-page: https://github.com/Thermondo/django-phaxio
Author: Thermondo GmbH
Author-email: opensource@thermondo.de
License: Apache-2
Keywords: django,phaxio
Platform: UNKNOWN
Classifier: Development Status :: 5 - Production/Stable
Classifier: Environment :: Web Environment
Classifier: Intended Audience :: Developers
Classifier: License :: OSI Approved :: Apache Software License
Classifier: Operating System :: OS Independent
Classifier: Programming Language :: Python
Classifier: Programming Language :: Python :: 3
Classifier: Framework :: Django
License-File: LICENSE
Requires-Dist: django (>=3.2)
Requires-Dist: django-appconf (>=1.0.1)
